pmconverter/__init__.py
pmconverter/basic_model.py
pmconverter/model_factory.py
pmconverter/pmconverter.py
pmconverter/prose_mirror_std_models.py
pmconverter/extensions/__init__.py
pmconverter/extensions/iwiki_models.py
prosemirror_py_converter-0.3.dist-info/LICENSE
prosemirror_py_converter-0.3.dist-info/METADATA
prosemirror_py_converter-0.3.dist-info/WHEEL
prosemirror_py_converter-0.3.dist-info/top_level.txt
prosemirror_py_converter-0.3.dist-info/RECORD
