Metadata-Version: 2.1
Name: prosemirror-py-converter
Version: 0.3
Summary: Python simple implementation of converting ProseMirror doc to markdown
Home-page: https://github.com/ghnjk/prosemirror-py-converter
Author: ghnjk
Author-email: ghnjk@foxmail.com
License: MIT
Keywords: prosemirror markdown pmconverter html python-converter
Classifier: Programming Language :: Python :: 3
Classifier: License :: OSI Approved :: MIT License
Classifier: Operating System :: OS Independent
License-File: LICENSE
